pygitrepo/.DS_Store
pygitrepo/__init__.py
pygitrepo/__init__.pyc
pygitrepo/_version.py
pygitrepo/_version.pyc
pygitrepo/actions.py
pygitrepo/actions.pyc
pygitrepo/cli.py
pygitrepo/color_print.py
pygitrepo/color_print.pyc
pygitrepo/constants.py
pygitrepo/constants.pyc
pygitrepo/helpers.py
pygitrepo/helpers.pyc
pygitrepo/operation_system.py
pygitrepo/operation_system.pyc
pygitrepo/repo_config.py
pygitrepo/repo_config.pyc
pygitrepo/__pycache__/__init__.cpython-38.pyc
pygitrepo/__pycache__/_version.cpython-38.pyc
pygitrepo/__pycache__/actions.cpython-38.pyc
pygitrepo/__pycache__/cli.cpython-38.pyc
pygitrepo/__pycache__/color_print.cpython-38.pyc
pygitrepo/__pycache__/constants.cpython-38.pyc
pygitrepo/__pycache__/helpers.cpython-38.pyc
pygitrepo/__pycache__/operation_system.cpython-38.pyc
pygitrepo/__pycache__/repo_config.cpython-38.pyc
pygitrepo/docs/__init__.py
pygitrepo/docs/__pycache__/__init__.cpython-38.pyc
pygitrepo/pkg/__init__.py
pygitrepo/pkg/__init__.pyc
pygitrepo/pkg/configirl.py
pygitrepo/pkg/configirl.pyc
pygitrepo/pkg/fingerprint.py
pygitrepo/pkg/fingerprint.pyc
pygitrepo/pkg/mini_colorma.py
pygitrepo/pkg/mini_colorma.pyc
pygitrepo/pkg/mini_six.py
pygitrepo/pkg/mini_six.pyc
pygitrepo/pkg/__pycache__/__init__.cpython-38.pyc
pygitrepo/pkg/__pycache__/configirl.cpython-38.pyc
pygitrepo/pkg/__pycache__/fingerprint.cpython-38.pyc
pygitrepo/pkg/__pycache__/mini_colorma.cpython-38.pyc
pygitrepo/pkg/__pycache__/mini_six.cpython-38.pyc
pygitrepo-1.0.8.dist-info/AUTHORS.rst
pygitrepo-1.0.8.dist-info/LICENSE.txt
pygitrepo-1.0.8.dist-info/METADATA
pygitrepo-1.0.8.dist-info/WHEEL
pygitrepo-1.0.8.dist-info/entry_points.txt
pygitrepo-1.0.8.dist-info/top_level.txt
pygitrepo-1.0.8.dist-info/RECORD
